educhain/__init__.py
educhain/core/__init__.py
educhain/core/config.py
educhain/core/educhain.py
educhain/engines/__init__.py
educhain/engines/content_engine.py
educhain/engines/qna_engine.py
educhain/models/__init__.py
educhain/models/base_models.py
educhain/models/content_models.py
educhain/models/pedagogy_models.py
educhain/models/qna_models.py
educhain/utils/__init__.py
educhain/utils/audio_utils.py
educhain/utils/loaders.py
educhain/utils/output_formatter.py
educhain-0.4.0.dist-info/LICENSE
educhain-0.4.0.dist-info/METADATA
educhain-0.4.0.dist-info/WHEEL
educhain-0.4.0.dist-info/top_level.txt
educhain-0.4.0.dist-info/RECORD
