Metadata-Version: 2.1
Name: educhain
Version: 0.4.0
Summary: A Python package for generating educational content using Generative AI
Home-page: https://github.com/satvik314/educhain
Author: Satvik Paramkusham
Author-email: satvik@buildfastwithai.com
Classifier: Development Status :: 3 - Alpha
Classifier: Intended Audience :: Developers
Classifier: License :: OSI Approved :: MIT License
Classifier: Programming Language :: Python :: 3
Classifier: Programming Language :: Python :: 3.10
Classifier: Programming Language :: Python :: 3.11
Classifier: Programming Language :: Python :: 3.12
Requires-Python: >=3.10
License-File: LICENSE
Requires-Dist: langchain>=1.0.0
Requires-Dist: langchain-openai>=1.1.0
Requires-Dist: langchain-community>=0.4.1
Requires-Dist: pydantic<3.0,>=2.0
Requires-Dist: langchain-text-splitters
Requires-Dist: langchain-google-genai
Requires-Dist: openai
Requires-Dist: python-dotenv
Requires-Dist: reportlab
Requires-Dist: PyPDF2
Requires-Dist: beautifulsoup4
Requires-Dist: youtube-transcript-api
Requires-Dist: requests
Requires-Dist: chromadb
Requires-Dist: protobuf
Requires-Dist: pillow
Requires-Dist: dataframe-image
Requires-Dist: pandas
Requires-Dist: ipython
Requires-Dist: matplotlib
Requires-Dist: numpy
Requires-Dist: gtts
Requires-Dist: pydub
Requires-Dist: mutagen
Provides-Extra: dev
Requires-Dist: pytest; extra == "dev"
Requires-Dist: black; extra == "dev"
Requires-Dist: flake8; extra == "dev"
